sequence_mining/__init__.py
sequence_mining/bitmap.py
sequence_mining/prefix.py
sequence_mining/spam.py
sequence_mining-0.0.3.dist-info/METADATA
sequence_mining-0.0.3.dist-info/WHEEL
sequence_mining-0.0.3.dist-info/licenses/LICENSE
sequence_mining-0.0.3.dist-info/RECORD
