Metadata-Version: 2.1
Name: sequence-mining
Version: 0.0.3
Summary: Sequence mining SPAM algorithm implementation
Project-URL: Homepage, https://github.com/adyachok/sequence-mining
Project-URL: Bug Tracker, https://github.com/adyachok/sequence-mining/issues
Author-email: Andras Gyacsok <atti.dyachok@gmail.com>
License: MIT License
License-File: LICENSE
Keywords: SPAM,sequence-mining
Classifier: License :: OSI Approved :: MIT License
Classifier: Operating System :: OS Independent
Classifier: Programming Language :: Python :: 3
Requires-Python: >=3.7
Requires-Dist: bitarray==2.6.0
Requires-Dist: bitmap==0.0.7
Requires-Dist: future==0.18.2
